napari_ome_zarr/__init__.py
napari_ome_zarr/_reader.py
napari_ome_zarr/_version.py
napari_ome_zarr/napari.yaml
napari_ome_zarr/_tests/__init__.py
napari_ome_zarr/_tests/test_reader.py
napari_ome_zarr-0.6.1.dist-info/LICENSE
napari_ome_zarr-0.6.1.dist-info/METADATA
napari_ome_zarr-0.6.1.dist-info/WHEEL
napari_ome_zarr-0.6.1.dist-info/entry_points.txt
napari_ome_zarr-0.6.1.dist-info/top_level.txt
napari_ome_zarr-0.6.1.dist-info/RECORD
