Metadata-Version: 2.1
Name: napari-ome-zarr
Version: 0.6.1
Summary: A reader for zarr backed OME-NGFF images.
Home-page: https://github.com/ome/napari-ome-zarr
Author: OME Team
Author-email: ome-team@openmicroscopy.org
License: BSD-3
Project-URL: Bug Tracker, https://github.com/ome/napari-ome-zarr/issues
Project-URL: Documentation, https://github.com/ome/napari-ome-zarr#README.md
Project-URL: Source Code, https://github.com/ome/napari-ome-zarr
Project-URL: User Support, https://github.com/ome/napari-ome-zarr/issues
Project-URL: Twitter, https://twitter.com/openmicroscopy
Classifier: Development Status :: 4 - Beta
Classifier: Intended Audience :: Developers
Classifier: Framework :: napari
Classifier: Topic :: Software Development :: Testing
Classifier: Programming Language :: Python
Classifier: Programming Language :: Python :: 3
Classifier: Programming Language :: Python :: 3.8
Classifier: Programming Language :: Python :: 3.9
Classifier: Programming Language :: Python :: 3.10
Classifier: Programming Language :: Python :: 3.11
Classifier: Operating System :: OS Independent
Classifier: License :: OSI Approved :: BSD License
Requires-Python: >=3.7
License-File: LICENSE
Requires-Dist: ome-zarr >=0.3.0
Requires-Dist: numpy
Requires-Dist: vispy
Requires-Dist: napari >=0.4.13
